{
  "card_id": "amex-hilton-surpass",
  "name": "Hilton Honors American Express Surpass Card",
  "issuer": "American Express",
  "network": "Amex",
  "annual_fee": 150,
  "foreign_transaction_fee": 0,
  "credit_required": "Good",
  "welcome_offer": {
    "spending_requirement": 3000,
    "time_period_months": 6,
    "bonus_points": 130000,
    "description": "Earn 130,000 Hilton Honors Bonus Points plus a Free Night Reward after spending $3,000 on eligible purchases within the first 6 months of card membership. Offer ends 4/15/26.",
    "free_nights": 1,
    "point_program": "Hilton Honors",
    "estimated_value": 500
  },
  "earning_rates": [
    {
      "category": "hotel_hilton",
      "rate": 12,
      "notes": "Hilton Honors Bonus Points per dollar at hotels and resorts within the Hilton portfolio"
    },
    {
      "category": "gas",
      "rate": 6,
      "notes": "U.S. gas stations"
    },
    {
      "category": "grocery",
      "rate": 6,
      "notes": "U.S. supermarkets"
    },
    {
      "category": "restaurant",
      "rate": 6,
      "notes": "U.S. restaurants"
    },
    {
      "category": "online_retail",
      "rate": 4,
      "notes": "U.S. online retail purchases"
    },
    {
      "category": "default",
      "rate": 3,
      "notes": "All other eligible purchases"
    }
  ],
  "travel_benefits": {
    "lounge_access": {
      "priority_pass": false,
      "centurion": false,
      "other": null
    },
    "hotel_status": [
      {
        "program": "Hilton Honors",
        "tier": "Gold",
        "method": "Automatic for as long as the card is open"
      },
      {
        "program": "Hilton Honors",
        "tier": "Diamond",
        "method": "Earned by spending $40,000 on eligible purchases in a calendar year (valid through end of next calendar year)"
      }
    ],
    "other_benefits": [
      {
        "name": "National Emerald Club Executive Status",
        "description": "Car rental status with National Car Rental (enrollment required)"
      },
      {
        "name": "Fifth Night Free",
        "description": "Fifth night free on reward stays (all Honors members)"
      }
    ]
  },
  "fhr_thc": {
    "fhr_eligible": false,
    "thc_eligible": false
  },
  "insurance": {
    "rental_insurance": "Secondary",
    "trip_delay": true,
    "purchase_protection": true,
    "extended_warranty": true
  },
  "tags": [
    "hotel",
    "premium"
  ],
  "sources": [
    {
      "url": "https://thepointsguy.com/credit-cards/hilton-honors-amex-current-offers/",
      "notes": "130K points + Free Night after $3K spend in 6 months, ends 4/15/26; earning rates 12x/6x/4x/3x"
    },
    {
      "url": "https://www.nerdwallet.com/credit-cards/news/hilton-new-welcome-offer-march-2026",
      "notes": "Confirmed 130K + 1FN offer per US Credit Card Guide 2026.2 update, offer ends 4/15/26"
    },
    {
      "url": "https://onemileatatime.com/deals/hilton-amex-card-bonus/",
      "notes": "Hilton Surpass benefits: $200 Hilton credits ($50/quarter), $150 AF, Gold\u2192Diamond path at $40K, National status"
    }
  ],
  "last_updated": "2026-04-16T13:41:49.948Z",
  "hotel_program": null,
  "application_rules": {
    "rules": [],
    "notes": null
  },
  "recurring_credits": [
    {
      "name": "Hilton Credits",
      "amount": 200,
      "frequency": "quarterly",
      "category": "hotel"
    },
    {
      "name": "Free Night Reward (spending)",
      "amount": null,
      "frequency": "annual",
      "category": "other"
    }
  ]
}