{
  "card_id": "wells-fargo-active-cash-biz",
  "name": "Active Cash Business",
  "issuer": "Wells Fargo",
  "network": "Visa",
  "annual_fee": 0,
  "foreign_transaction_fee": 0,
  "credit_required": "Good",
  "welcome_offer": {
    "bonus_points": 0,
    "description": "No welcome bonus",
    "estimated_value": null,
    "spending_requirement": null,
    "time_period_months": null
  },
  "earning_rates": [
    {
      "category": "All Purchases",
      "rate": 2,
      "notes": "unlimited"
    }
  ],
  "annual_credits": [],
  "travel_benefits": {
    "hotel_status": [],
    "other_benefits": [],
    "lounge_access": {
      "centurion": false,
      "priority_pass": false
    }
  },
  "fhr_thc": {
    "fhr_eligible": false,
    "thc_eligible": false
  },
  "insurance": {
    "trip_cancellation": null,
    "trip_delay": null,
    "rental_insurance": null,
    "purchase_protection": null,
    "return_protection": null,
    "extended_warranty": null,
    "baggage_delay": null,
    "lost_luggage": null,
    "cell_phone": null,
    "travel_accident": null
  },
  "tags": [
    "business",
    "no-annual-fee"
  ],
  "sources": [],
  "benefits": [],
  "hotel_program": null,
  "application_rules": {
    "rules": [],
    "notes": null
  },
  "last_updated": "2026-04-16T13:41:50.010Z"
}