{
  "items": [
    {
      "title": "Cardless Giving Large Unsolicited Credit Limit Increases On Bilt Palladium Cards",
      "url": "https://www.doctorofcredit.com/cardless-giving-large-unsolicited-credit-limit-increases-on-bilt-palladium-cards/",
      "source": "Doctor of Credit",
      "categories": [
        "Credit Cards",
        "bilt"
      ],
      "ts": "2026-05-31T20:47:13.000Z",
      "title_en": "Cardless Giving Large Unsolicited Credit Limit Increases On Bilt Palladium Cards",
      "summary_en": "",
      "title_zh": "Cardless 為 Bilt Palladium 卡提供大幅未被要求的信用額度提升",
      "summary_zh": "Cardless 宣布對 Bilt Palladium 卡大幅自動提升信用額度，無需申請。",
      "title_es": "Cardless ofrece grandes aumentos no solicitados en el límite de crédito de las tarjetas Bilt Palladium",
      "summary_es": "Cardless ha comenzado a aumentar automáticamente el límite de crédito en las tarjetas Bilt Palladium sin que los tarjetahabientes lo soliciten."
    },
    {
      "title": "Discover Q3 2026 5% Categories: Gas/EV, Transit, Flights, Drugstores",
      "url": "https://www.doctorofcredit.com/discover-q2-2026-5-categories-gas-ev-transit-flights-drugstores/",
      "source": "Doctor of Credit",
      "categories": [
        "Deals",
        "discover"
      ],
      "ts": "2026-05-31T20:24:29.000Z",
      "title_en": "Discover Q3 2026 5% Categories: Gas/EV, Transit, Flights, Drugstores",
      "summary_en": "",
      "title_zh": "Discover 2026 年第三季度 5% 回饋類別：汽油/電動車、公交、機票、藥局",
      "summary_zh": "Discover 公佈 2026 年第三季 5% 回饋類別，包括加油、電動車、公交、機票和藥局消費。",
      "title_es": "Discover Q3 2026 categorías al 5%: gasolina/VE, transporte, vuelos y farmacias",
      "summary_es": "Discover ha revelado las categorías de devolución del 5% para el tercer trimestre de 2026, que incluyen gasolina/vehículo eléctrico, transporte público, vuelos y farmacias."
    },
    {
      "title": "[AL, GA] Five Star Credit Union $200 Checking Bonus",
      "url": "https://www.doctorofcredit.com/al-ga-five-star-credit-union-200-checking-bonus/",
      "source": "Doctor of Credit",
      "categories": [
        "Bank Accounts",
        "al bank bonuses",
        "direct deposit required",
        "ga bank bonuses",
        "no credit card funding",
        "soft pull"
      ],
      "ts": "2026-05-31T19:00:52.000Z",
      "title_en": "[AL, GA] Five Star Credit Union $200 Checking Bonus",
      "summary_en": "",
      "title_zh": "[阿拉巴馬州、喬治亞州] Five Star Credit Union $200 支票帳戶獎金",
      "summary_zh": "Five Star Credit Union 在阿拉巴馬與喬治亞州推出 $200 支票帳戶開戶獎金。",
      "title_es": "[AL, GA] Five Star Credit Union bono de $200 por cuenta corriente",
      "summary_es": "Five Star Credit Union ofrece un bono de $200 por abrir una cuenta corriente en Alabama y Georgia."
    },
    {
      "title": "[MO, KS, In Branch Only] OMB Bank $250 Checking Bonus",
      "url": "https://www.doctorofcredit.com/mo-ks-in-branch-only-omb-bank-250-checking-bonus/",
      "source": "Doctor of Credit",
      "categories": [
        "Bank Accounts",
        "direct deposit required",
        "ks bank bonuses",
        "mo bank bonuses"
      ],
      "ts": "2026-05-31T18:00:51.000Z",
      "title_en": "[MO, KS, In Branch Only] OMB Bank $250 Checking Bonus",
      "summary_en": "",
      "title_zh": "[密蘇里州、堪薩斯州，僅限分行] OMB Bank $250 支票帳戶獎金",
      "summary_zh": "OMB Bank 在密蘇里與堪薩斯州的分支機構提供 $250 支票帳戶開戶獎金。",
      "title_es": "[MO, KS, solo en sucursal] OMB Bank bono de $250 por cuenta corriente",
      "summary_es": "OMB Bank ofrece un bono de $250 para nuevas cuentas corrientes en Missouri y Kansas, disponible solo en sucursal."
    },
    {
      "title": "[NJ, NY & PA, In branch only] Provident Bank $300-$750 Business Checking Bonus",
      "url": "https://www.doctorofcredit.com/nj-ny-pa-in-branch-only-provident-bank-300-750-business-checking-bonus/",
      "source": "Doctor of Credit",
      "categories": [
        "Bank Accounts",
        "credit card funding",
        "direct deposit not required",
        "nj bank bonuses",
        "ny bank bonuses",
        "pa bank bonuses",
        "soft pull"
      ],
      "ts": "2026-05-31T17:30:04.000Z",
      "title_en": "[NJ, NY & PA, In branch only] Provident Bank $300-$750 Business Checking Bonus",
      "summary_en": "",
      "title_zh": "[新澤西州、紐約州及賓夕法尼亞州，僅限分行] Provident Bank $300-$750 企業支票帳戶獎金",
      "summary_zh": "Provident Bank 在新澤西、紐約與賓州的分支機構推出 $300 至 $750 的企業支票帳戶獎金。",
      "title_es": "[NJ, NY y PA, solo en sucursal] Provident Bank bono de $300-$750 por cuenta corriente empresarial",
      "summary_es": "Provident Bank ofrece un bono entre $300 y $750 por abrir una cuenta corriente empresarial en Nueva Jersey, Nueva York y Pensilvania, solo en sucursal."
    },
    {
      "title": "[Houston Area, TX] Members Choice Credit Union $300 Checking Bonus",
      "url": "https://www.doctorofcredit.com/houston-area-tx-members-choice-credit-union-300-checking-bonus/",
      "source": "Doctor of Credit",
      "categories": [
        "Bank Accounts",
        "direct deposit required",
        "tx bank bonuses"
      ],
      "ts": "2026-05-31T17:00:16.000Z",
      "title_en": "[Houston Area, TX] Members Choice Credit Union $300 Checking Bonus",
      "summary_en": "",
      "title_zh": "[德克薩斯州休士頓地區] Members Choice Credit Union $300 支票帳戶獎金",
      "summary_zh": "Members Choice Credit Union 在休士頓地區提供 $300 支票帳戶開戶獎金。",
      "title_es": "[Área de Houston, TX] Members Choice Credit Union bono de $300 por cuenta corriente",
      "summary_es": "Members Choice Credit Union ofrece un bono de $300 por abrir una cuenta corriente en el área de Houston, Texas."
    },
    {
      "title": "[FL, NJ, NY] Popular Bank $400 Business Checking Bonus",
      "url": "https://www.doctorofcredit.com/fl-nj-ny-popular-bank-400-business-checking-bonus/",
      "source": "Doctor of Credit",
      "categories": [
        "Bank Accounts",
        "fl bank bonuses",
        "nj bank bonuses",
        "ny bank bonuses",
        "soft pull"
      ],
      "ts": "2026-05-31T16:30:02.000Z",
      "title_en": "[FL, NJ, NY] Popular Bank $400 Business Checking Bonus",
      "summary_en": "",
      "title_zh": "[佛羅里達州、新澤西州、紐約州] Popular Bank $400 企業支票帳戶獎金",
      "summary_zh": "Popular Bank 在佛羅里達、新澤西和紐約推出 $400 企業支票帳戶獎金。",
      "title_es": "[FL, NJ, NY] Popular Bank bono de $400 por cuenta corriente empresarial",
      "summary_es": "Popular Bank ofrece un bono de $400 por abrir una cuenta corriente empresarial en Florida, Nueva Jersey y Nueva York."
    },
    {
      "title": "[IN & MI] Horizon Bank $250 Checking Bonus",
      "url": "https://www.doctorofcredit.com/in-in-branch-only-horizon-bank-300-checking-bonus/",
      "source": "Doctor of Credit",
      "categories": [
        "Bank Accounts",
        "direct deposit required",
        "in bank bonuses",
        "soft pull"
      ],
      "ts": "2026-05-31T16:00:21.000Z",
      "title_en": "[IN & MI] Horizon Bank $250 Checking Bonus",
      "summary_en": "",
      "title_zh": "[印第安納州與密歇根州] Horizon Bank $250 支票帳戶獎金",
      "summary_zh": "Horizon Bank 在印第安納與密歇根州提供 $250 支票帳戶開戶獎金。",
      "title_es": "[IN y MI] Horizon Bank bono de $250 por cuenta corriente",
      "summary_es": "Horizon Bank ofrece un bono de $250 para nuevas cuentas corrientes en Indiana y Michigan."
    },
    {
      "title": "[CA Only?] OceanAir Credit Card – 5% Back On Gas/Travel, 4% Back On Warehouse Clubs & More",
      "url": "https://www.doctorofcredit.com/ca-only-oceanair-credit-card-5-back-on-gas-travel-4-back-on-warehouse-clubs-more/",
      "source": "Doctor of Credit",
      "categories": [
        "Credit Cards"
      ],
      "ts": "2026-05-31T15:30:00.000Z",
      "title_en": "[CA Only?] OceanAir Credit Card – 5% Back On Gas/Travel, 4% Back On Warehouse Clubs & More",
      "summary_en": "",
      "title_zh": "[僅加州？] OceanAir 信用卡 – 加油/旅行 5% 回饋，倉儲 club 4% 回饋等",
      "summary_zh": "OceanAir 信用卡針對加油與旅行提供 5% 回饋，倉儲會員消費則有 4% 回饋。",
      "title_es": "[¿Solo en CA?] Tarjeta de crédito OceanAir – 5% de regreso en gasolina/viajes, 4% en clubes de almacén y más",
      "summary_es": "La tarjeta OceanAir ofrece un 5% de devolución en gasolina y viajes, y un 4% en clubes de almacén, entre otras categorías."
    },
    {
      "title": "[IL only] U of I Community Credit Union $150 Checking Bonus, Direct Deposit Not Required",
      "url": "https://www.doctorofcredit.com/il-only-u-of-i-community-credit-union-150-checking-bonus-direct-deposit-not-required/",
      "source": "Doctor of Credit",
      "categories": [
        "Bank Accounts",
        "direct deposit not required",
        "IL bank bonuses",
        "soft pull"
      ],
      "ts": "2026-05-31T15:00:03.000Z",
      "title_en": "[IL only] U of I Community Credit Union $150 Checking Bonus, Direct Deposit Not Required",
      "summary_en": "",
      "title_zh": "[僅伊利諾州] 伊利諾大學社區信用合作社 $150 支票帳戶獎金，無需直接存款",
      "summary_zh": "伊利諾大學社區信用合作社在伊利諾州提供 $150 支票帳戶獎金，且不要求直接存款。",
      "title_es": "[Solo en IL] U of I Community Credit Union bono de $150 por cuenta corriente, no requiere depósito directo",
      "summary_es": "U of I Community Credit Union ofrece un bono de $150 por abrir una cuenta corriente en Illinois sin necesidad de realizar un depósito directo."
    },
    {
      "title": "[WA only] WSECU $300 Checking Bonus",
      "url": "https://www.doctorofcredit.com/wa-only-wsecu-300-checking-bonus/",
      "source": "Doctor of Credit",
      "categories": [
        "Bank Accounts",
        "credit card funding",
        "direct deposit required",
        "soft pull",
        "wa bank bonuses"
      ],
      "ts": "2026-05-31T14:30:56.000Z",
      "title_en": "[WA only] WSECU $300 Checking Bonus",
      "summary_en": "",
      "title_zh": "[僅華盛頓州] WSECU $300 支票帳戶獎金",
      "summary_zh": "WSECU 在華盛頓州推出 $300 支票帳戶開戶獎金。",
      "title_es": "[Solo en WA] WSECU bono de $300 por cuenta corriente",
      "summary_es": "WSECU ofrece un bono de $300 por abrir una cuenta corriente en Washington."
    },
    {
      "title": "[NY] Suffolk Federal Credit Union $500 Checking Bonus",
      "url": "https://www.doctorofcredit.com/ny-suffolk-federal-credit-union-100-checking-bonus-direct-deposit-not-required/",
      "source": "Doctor of Credit",
      "categories": [
        "Bank Accounts",
        "credit card funding",
        "direct deposit not required",
        "ny bank bonuses"
      ],
      "ts": "2026-05-31T14:00:41.000Z",
      "title_en": "[NY] Suffolk Federal Credit Union $500 Checking Bonus",
      "summary_en": "",
      "title_zh": "[紐約州] Suffolk Federal Credit Union $500 支票帳戶獎金",
      "summary_zh": "Suffolk Federal Credit Union 在紐約州提供 $500 支票帳戶開戶獎金。",
      "title_es": "[NY] Suffolk Federal Credit Union bono de $500 por cuenta corriente",
      "summary_es": "Suffolk Federal Credit Union ofrece un bono de $500 por abrir una cuenta corriente en Nueva York."
    },
    {
      "title": "[AL Only] Alabama Central Credit Union $100 Referral Bonus, Direct Deposit Not Required",
      "url": "https://www.doctorofcredit.com/al-only-alabama-central-credit-union-100-referral-bonus-direct-deposit-not-required/",
      "source": "Doctor of Credit",
      "categories": [
        "Bank Accounts",
        "al bank bonuses",
        "credit card funding",
        "direct deposit required"
      ],
      "ts": "2026-05-31T13:30:54.000Z",
      "title_en": "[AL Only] Alabama Central Credit Union $100 Referral Bonus, Direct Deposit Not Required",
      "summary_en": "",
      "title_zh": "[僅阿拉巴馬州] Alabama Central Credit Union $100 推薦獎金，無需直接存款",
      "summary_zh": "Alabama Central Credit Union 在阿拉巴馬州提供 $100 推薦獎金，且不要求直接存款。",
      "title_es": "[Solo en AL] Alabama Central Credit Union bono de $100 por referido, no requiere depósito directo",
      "summary_es": "Alabama Central Credit Union ofrece un bono de $100 por cada referido queabra una cuenta, sin necesidad de un depósito directo."
    },
    {
      "title": "Staples: No Purchase Fee On $200 Visa Gift Cards (5/31-6/5)",
      "url": "https://www.doctorofcredit.com/staples-no-purchase-fee-on-200-visa-gift-cards-10-31-11-6-limit-5/",
      "source": "Doctor of Credit",
      "categories": [
        "Manufactured Spending",
        "staples",
        "visa gift cards"
      ],
      "ts": "2026-05-31T13:00:28.000Z",
      "title_en": "Staples: No Purchase Fee On $200 Visa Gift Cards (5/31-6/5)",
      "summary_en": "",
      "title_zh": "Staples：$200 Visa 禮卡免購買手續費（5/31-6/5）",
      "summary_zh": "Staples 在 5 月 31 日至 6 月 5 日期間，所有 $200 Visa 禮卡均免收購買手續費。",
      "title_es": "Staples: Sin cargo de compra en tarjetas de regalo Visa de $200 (5/31-6/5)",
      "summary_es": "Staples no cobra tarifa de compra en tarjetas de regalo Visa de $200 durante el período del 31 de mayo al 5 de junio."
    },
    {
      "title": "[IA Only] FSB Bank $300-$1,000 Business Checking Bonus",
      "url": "https://www.doctorofcredit.com/ia-only-fsb-bank-500-business-checking-bonus-requires-payroll-processing/",
      "source": "Doctor of Credit",
      "categories": [
        "Bank Accounts",
        "direct deposit not required",
        "ia bank bonuses"
      ],
      "ts": "2026-05-31T12:00:30.000Z",
      "title_en": "[IA Only] FSB Bank $300-$1,000 Business Checking Bonus",
      "summary_en": "",
      "title_zh": "[僅愛荷華州] FSB Bank $300-$1,000 企業支票帳戶獎金",
      "summary_zh": "FSB Bank 在愛荷華州推出 $300 至 $1,000 的企業支票帳戶開戶獎金。",
      "title_es": "[Solo en IA] FSB Bank bono de $300-$1,000 por cuenta corriente empresarial",
      "summary_es": "FSB Bank ofrece un bono entre $300 y $1,000 por abrir una cuenta corriente empresarial en Iowa."
    }
  ],
  "fetched": "2026-06-01T02:09:38.491Z"
}