{
  "items": [
    {
      "title": "[Targeted] Chase Business Checking Bonus – Up To $1,500",
      "url": "https://www.doctorofcredit.com/targeted-chase-business-checking-bonus-up-to-1500/",
      "source": "Doctor of Credit",
      "categories": [
        "Bank Accounts",
        "chase"
      ],
      "ts": "2026-04-29T19:00:26.000Z",
      "title_en": "[Targeted] Chase Business Checking Bonus – Up To $1,500",
      "summary_en": "",
      "title_zh": "[目標] 摩根大通商業支票獎勵 – 最高可達 $1,500",
      "summary_zh": "此優惠為摩根大通商業支票帳戶提供高達$1,500的現金獎勵，詳情視客戶資格而定。",
      "title_es": "[Dirigido] Bono de Cuenta Corriente Empresarial de Chase – Hasta $1,500",
      "summary_es": "Chase ofrece un bono de hasta $1,500 para nuevos clientes de cuentas corrientes empresariales."
    },
    {
      "title": "TSA PreCheck: $20 Savings For Those Age 30 Or Younger",
      "url": "https://www.doctorofcredit.com/tsa-precheck-20-savings-for-those-age-30-or-younger/",
      "source": "Doctor of Credit",
      "categories": [
        "Travel",
        "tsa precheck"
      ],
      "ts": "2026-04-29T18:36:19.000Z",
      "title_en": "TSA PreCheck: $20 Savings For Those Age 30 Or Younger",
      "summary_en": "",
      "title_zh": "TSA PreCheck：30歲或以下人士可節省 $20",
      "summary_zh": "符合年齡條件的旅客在30歲或以下可享有TSA PreCheck $20的費用減免。",
      "title_es": "TSA PreCheck: Ahorro de $20 para Personas de 30 Años o Menores",
      "summary_es": "Los viajeros de 30 años o menores pueden beneficiarse de un descuento de $20 en TSA PreCheck."
    },
    {
      "title": "H-E-B Stores: Buy $100 Select Giftcards, Get $20 H-E-B Giftcard (Airbnb, Ulta, Wayfair & More)",
      "url": "https://www.doctorofcredit.com/h-e-b-stores-buy-100-select-giftcards-get-20-h-e-b-giftcard-airbnb-ulta-wayfair-more/",
      "source": "Doctor of Credit",
      "categories": [
        "Gift Card Deals",
        "h-e-b"
      ],
      "ts": "2026-04-29T18:32:04.000Z",
      "title_en": "H-E-B Stores: Buy $100 Select Giftcards, Get $20 H-E-B Giftcard (Airbnb, Ulta, Wayfair & More)",
      "summary_en": "",
      "title_zh": "H-E-B 超市：購買 $100 指定禮卡，獲赠 $20 H-E-B 禮卡（Airbnb、Ulta、Wayfair 等）",
      "summary_zh": "在H-E-B超市購買指定禮卡滿$100即可獲得$20的H-E-B禮卡，可用於Airbnb、Ulta、Wayfair等多種品牌。",
      "title_es": "H-E-B Stores: Compra $100 en Tarjetas de Regalo Seleccionadas, Obtén $20 en Tarjeta de Regalo de H-E-B (Airbnb, Ulta, Wayfair y Más)",
      "summary_es": "En H-E-B, al comprar $100 en tarjetas de regalo seleccionadas recibirás una tarjeta de regalo adicional de $20."
    },
    {
      "title": "Bestbuy.com: Save 10% On Uber & Chipotle eGiftcards",
      "url": "https://www.doctorofcredit.com/bestbuy-com-save-10-on-uber-chipotle-egiftcards/",
      "source": "Doctor of Credit",
      "categories": [
        "Gift Card Deals",
        "best buy",
        "Chipotle",
        "Uber"
      ],
      "ts": "2026-04-29T18:23:31.000Z",
      "title_en": "Bestbuy.com: Save 10% On Uber & Chipotle eGiftcards",
      "summary_en": "",
      "title_zh": "Bestbuy.com：Uber 與 Chipotle 電子禮卡享 10% 折扣",
      "summary_zh": "在Bestbuy.com購買Uber或Chipotle電子禮卡可享受10%的優惠折扣。",
      "title_es": "Bestbuy.com: Ahorra 10% en Tarjetas de Regalo Electrónicas de Uber y Chipotle",
      "summary_es": "Best Buy ofrece un 10% de descuento en tarjetas de regalo electrónicas de Uber y Chipotle."
    },
    {
      "title": "Save 10% On Instacart Giftcards (Max $20 Savings)",
      "url": "https://www.doctorofcredit.com/save-10-on-instacart-giftcards-max-20-savings/",
      "source": "Doctor of Credit",
      "categories": [
        "Gift Card Deals",
        "instacart"
      ],
      "ts": "2026-04-29T17:57:19.000Z",
      "title_en": "Save 10% On Instacart Giftcards (Max $20 Savings)",
      "summary_en": "",
      "title_zh": "Instacart 禮卡 10% 折扣（最高可省 $20）",
      "summary_zh": "Instacart禮卡優惠高達10%折扣，最高可節省$20。",
      "title_es": "Ahorra 10% en Tarjetas de Regalo de Instacart (Ahorro Máximo de $20)",
      "summary_es": "Instacart permite un ahorro del 10% en sus tarjetas de regalo, hasta $20."
    },
    {
      "title": "Capital One Shopping/Offers: 4%-20% Back On Giftcards.com",
      "url": "https://www.doctorofcredit.com/capital-one-shopping-offers-4-20-back-on-giftcards-com/",
      "source": "Doctor of Credit",
      "categories": [
        "Gift Card Deals",
        "capital one shopping",
        "giftcards.com"
      ],
      "ts": "2026-04-29T17:41:52.000Z",
      "title_en": "Capital One Shopping/Offers: 4%-20% Back On Giftcards.com",
      "summary_en": "",
      "title_zh": "Capital One 購物/優惠：Giftcards.com 回饋 4%-20%",
      "summary_zh": "該優惠在 Giftcards.com 上提供 4% 到 20% 的回饋，適用於 Capital One 購物。",
      "title_es": "Capital One Shopping/Ofertas: 4%-20% de devolución en Giftcards.com",
      "summary_es": "Capital One ofrece entre un 4% y un 20% de devolución en las compras realizadas a través de Giftcards.com."
    },
    {
      "title": "[Summer Pass For $199] Frontier All You Can Fly ‘GoWild!’ Pass",
      "url": "https://www.doctorofcredit.com/frontier-to-launch-all-you-can-fly-gowild-pass/",
      "source": "Doctor of Credit",
      "categories": [
        "Travel",
        "frontier airlines"
      ],
      "ts": "2026-04-29T15:00:42.000Z",
      "title_en": "[Summer Pass For $199] Frontier All You Can Fly ‘GoWild!’ Pass",
      "summary_en": "",
      "title_zh": "[199 美元夏季通行證] Frontier「GoWild!」無限飛行通行證",
      "summary_zh": "只需 199 美元即可在 Frontier 享受整個夏季的無限飛行，稱為 GoWild! 通行證。",
      "title_es": "[Pase de Verano por $199] Frontier 'GoWild!' Pasaje Ilimitado",
      "summary_es": "Frontier lanza un pase de verano por $199 que permite volar de forma ilimitada con su programa 'GoWild!'."
    },
    {
      "title": "Best Current Credit Card Sign Up Bonuses & Offers For April, 2026",
      "url": "https://www.doctorofcredit.com/best-current-credit-card-sign-bonuses/",
      "source": "Doctor of Credit",
      "categories": [
        "Credit Cards",
        "signup bonus"
      ],
      "ts": "2026-04-29T14:00:15.000Z",
      "title_en": "Best Current Credit Card Sign Up Bonuses & Offers For April, 2026",
      "summary_en": "",
      "title_zh": "2026 年 4 月最佳信用卡開卡獎勵與優惠",
      "summary_zh": "本文整理了 2026 年 4 月最具吸引力的信用卡開卡獎勵與優惠資訊。",
      "title_es": "Los Mejores Bonos de Registro y Ofertas de Tarjetas de Crédito para Abril de 2026",
      "summary_es": "Un resumen de los mayores bonos de bienvenida y ofertas disponibles en las tarjetas de crédito durante abril de 2026."
    },
    {
      "title": "Sam’s Club: $500 Disney Giftcard For $450 (4/29 – 5/31)",
      "url": "https://www.doctorofcredit.com/sams-club-500-disney-giftcard-for-450-11-25-11-28/",
      "source": "Doctor of Credit",
      "categories": [
        "Deals",
        "disney",
        "sam's club"
      ],
      "ts": "2026-04-29T13:00:06.000Z",
      "title_en": "Sam’s Club: $500 Disney Giftcard For $450 (4/29 – 5/31)",
      "summary_en": "",
      "title_zh": "Sam’s Club：迪士尼禮品卡 500 美元只要 450 美元（4/29 – 5/31）",
      "summary_zh": "Sam’s Club 推出特價促銷，迪士尼 500 美元禮品卡僅售 450 美元，限期至 5 月 31 日。",
      "title_es": "Sam’s Club: Tarjeta de Regalo Disney de $500 por $450 (29/4 – 31/5)",
      "summary_es": "Sam’s Club vende tarjetas de regalo Disney con valor de $500 a un precio reducido de $450 durante el período del 29 de abril al 31 de mayo."
    },
    {
      "title": "Recap: Free Month Of AwardLocker, Air Canada Raises Prices, Citibank $2,500 In Branch Offer & More",
      "url": "https://www.doctorofcredit.com/recap-free-month-of-awardlocker-air-canada-raises-prices-citibank-2500-in-branch-offer-more/",
      "source": "Doctor of Credit",
      "categories": [
        "Recaps"
      ],
      "ts": "2026-04-29T12:00:50.000Z",
      "title_en": "Recap: Free Month Of AwardLocker, Air Canada Raises Prices, Citibank $2,500 In Branch Offer & More",
      "summary_en": "",
      "title_zh": "摘要：AwardLocker 免費一個月、加拿大航空調漲價格、花旗銀行 2,500 美元分行優惠及其他",
      "summary_zh": "本週回顧包括 AwardLocker 免費一個月、Air Canada 票價上漲、花旗銀行的 2,500 美元分行優惠等多項資訊。",
      "title_es": "Resumen: Mes Gratis de AwardLocker, Air Canada Sube Precios, Oferta de Citibank de $2,500 en Sucursal y Más",
      "summary_es": "Este resumen incluye un mes gratuito de AwardLocker, el aumento de precios de Air Canada, una oferta de Citibank de $2,500 en sucursal y otras novedades."
    },
    {
      "title": "Why Do We Close Referral Threads After A Period Of Time?",
      "url": "https://www.doctorofcredit.com/why-do-we-close-referral-threads-after-a-period-of-time/",
      "source": "Doctor of Credit",
      "categories": [
        "Site News",
        "referral",
        "referrals",
        "rules"
      ],
      "ts": "2026-04-29T01:56:41.000Z",
      "title_en": "Why Do We Close Referral Threads After A Period Of Time?",
      "summary_en": "",
      "title_zh": "為什麼我們在一定時間後關閉推薦討論串？",
      "summary_zh": "我們在一定時間後關閉推薦討論串，以控制討論品質並防止濫用。",
      "title_es": "¿Por qué cerramos los hilos de referidos después de un período de tiempo?",
      "summary_es": "Los hilos de referidos se cierran tras un tiempo para mantener la relevancia y evitar contenido obsoleto."
    },
    {
      "title": "Alliant Credit Union $150 Checking Bonus",
      "url": "https://www.doctorofcredit.com/rakuten-alliant-credit-union-100-10000-checking-bonus/",
      "source": "Doctor of Credit",
      "categories": [
        "Bank Accounts",
        "bank bonus",
        "direct deposit required",
        "nationwide bank bonuses"
      ],
      "ts": "2026-04-29T00:05:06.000Z",
      "title_en": "Alliant Credit Union $150 Checking Bonus",
      "summary_en": "",
      "title_zh": "Alliant Credit Union 150美元支票帳戶獎金",
      "summary_zh": "Alliant Credit Union 為新開支票帳戶的客戶提供150美元的獎金優惠。",
      "title_es": "Alliant Credit Union – Bono de $150 por cuenta corriente",
      "summary_es": "Alliant Credit Union ofrece un bono de $150 para nuevas cuentas corrientes."
    },
    {
      "title": "Chase IHG Premier Business Card – 200,000 Points Offer [Ends 4/29/26]",
      "url": "https://www.doctorofcredit.com/chase-ihg-premier-business-card-200000-offer-new-all-time-high/",
      "source": "Doctor of Credit",
      "categories": [
        "Credit Cards",
        "big",
        "chase",
        "chase ihg",
        "chase ihg business",
        "credit card bonuses",
        "ihg"
      ],
      "ts": "2026-04-28T23:15:43.000Z",
      "title_en": "Chase IHG Premier Business Card – 200,000 Points Offer [Ends 4/29/26]",
      "summary_en": "",
      "title_zh": "Chase IHG Premier 商務卡 – 200,000 點數優惠 [截止至2026年4月29日]",
      "summary_zh": "Chase IHG Premier 商務卡提供最高200,000點數的獎勵，優惠至2026年4月29日截止。",
      "title_es": "Tarjeta Chase IHG Premier Business – Oferta de 200,000 puntos [Termina el 29/04/26]",
      "summary_es": "Chase ofrece 200,000 puntos con la tarjeta IHG Premier Business hasta el 29 de abril de 2026."
    },
    {
      "title": "[YMMV] inKind: $5 Off $10+ When You Enable Notifications",
      "url": "https://www.doctorofcredit.com/ymmv-inkind-5-off-10-when-you-enable-notifications/",
      "source": "Doctor of Credit",
      "categories": [
        "Deals",
        "inkind"
      ],
      "ts": "2026-04-28T22:03:07.000Z",
      "title_en": "[YMMV] inKind: $5 Off $10+ When You Enable Notifications",
      "summary_en": "",
      "title_zh": "[YMMV] inKind：開啟通知後，消費10美元以上可享5美元折扣",
      "summary_zh": "inKind 在啟用通知後，對10美元以上的消費提供5美元的折扣優惠（優惠可能因人而異）。",
      "title_es": "[YMMV] inKind: $5 de descuento en $10+ al activar notificaciones",
      "summary_es": "InKind ofrece un descuento de $5 en compras de $10 o más al habilitar las notificaciones."
    },
    {
      "title": "American Express Transfer Bonus: 20% To Hilton Honors (1:2.4)",
      "url": "https://www.doctorofcredit.com/american-express-transfer-bonus-20-to-hilton-honors-12-4/",
      "source": "Doctor of Credit",
      "categories": [
        "Credit Cards",
        "american express",
        "american express transfer bonuses",
        "hilton",
        "transfer bonuses"
      ],
      "ts": "2026-04-28T21:59:34.000Z",
      "title_en": "American Express Transfer Bonus: 20% To Hilton Honors (1:2.4)",
      "summary_en": "",
      "title_zh": "American Express 轉帳獎勵：20% 獎勵至希爾頓榮譽客會 (1:2.4)",
      "summary_zh": "美國運通轉帳至希爾頓榮譽客會可獲得20%的額外獎勵，相當於1美元兌2.4點。",
      "title_es": "Bonificación de transferencia de American Express: 20% a Hilton Honors (1:2.4)",
      "summary_es": "American Express concede una bonificación del 20% al transferir puntos a Hilton Honors con una ratio de 1:2.4."
    }
  ],
  "fetched": "2026-04-29T20:02:52.620Z"
}