{
  "items": [
    {
      "title": "(Update) ShopBack Shopping Portal $15+ In Signup Bonuses & More; Earn Cashback On Amazon & More",
      "url": "https://www.doctorofcredit.com/shopback-shopping-portal-20-signup-bonus-earn-cashback-on-amazon-ubereats-more/",
      "source": "Doctor of Credit",
      "categories": [
        "Deals",
        "Shopping",
        "Free money",
        "shopping portals",
        "signup bonus"
      ],
      "ts": "2026-04-23T23:16:39.000Z",
      "title_en": "(Update) ShopBack Shopping Portal $15+ In Signup Bonuses & More; Earn Cashback On Amazon & More",
      "summary_en": "",
      "title_zh": "(Update) ShopBack Shopping Portal $15+ In Signup Bonuses & More; Earn Cashback On Amazon & More",
      "summary_zh": "",
      "title_es": "(Actualización) Portal de compras ShopBack: $15+ en bonos de registro y más; Gana cashback en Amazon y más.",
      "summary_es": "ShopBack está ofreciendo un bono de registro de al menos $15 y la posibilidad de obtener reembolso en compras en Amazon."
    },
    {
      "title": "[YMMV] DoorDash DashPass Trivia: $5 Off $12 When Answering 5 Questions Correctly",
      "url": "https://www.doctorofcredit.com/ymmv-doordash-dashpass-trivia-10-off-12-when-answering-5-questions-correctly/",
      "source": "Doctor of Credit",
      "categories": [
        "Deals",
        "dashpass",
        "doordash",
        "Food Delivery"
      ],
      "ts": "2026-04-23T22:51:29.000Z",
      "title_en": "[YMMV] DoorDash DashPass Trivia: $5 Off $12 When Answering 5 Questions Correctly",
      "summary_en": "",
      "title_zh": "[YMMV] DoorDash DashPass Trivia: $5 Off $12 When Answering 5 Questions Correctly",
      "summary_zh": "",
      "title_es": "[YMMV] Trivia de DoorDash DashPass: $5 de descuento en $12 al responder correctamente 5 preguntas.",
      "summary_es": "Los usuarios pueden obtener un descuento de $5 al gastar $12 si responden correctamente cinco preguntas en la trivia de DashPass."
    },
    {
      "title": "Pizza Hut: Book It, Read Books & Earn Pizzas (Ages 5-12)",
      "url": "https://www.doctorofcredit.com/pizza-hut-book-it-read-books-earn-pizzas-ages-5-12/",
      "source": "Doctor of Credit",
      "categories": [
        "Deals",
        "free food",
        "freebies"
      ],
      "ts": "2026-04-23T22:40:41.000Z",
      "title_en": "Pizza Hut: Book It, Read Books & Earn Pizzas (Ages 5-12)",
      "summary_en": "",
      "title_zh": "Pizza Hut: Book It, Read Books & Earn Pizzas (Ages 5-12)",
      "summary_zh": "",
      "title_es": "Pizza Hut: Apúntalo, Lee libros y Gana pizzas (Edades 5-12).",
      "summary_es": "Pizza Hut ofrece un programa para niños de 5 a 12 años donde pueden ganar pizzas al leer libros."
    },
    {
      "title": "Xfinity Rewards: Free $10 GrubHub Giftcard",
      "url": "https://www.doctorofcredit.com/xfinity-rewards-free-10-ubereats-grubhub-giftcard/",
      "source": "Doctor of Credit",
      "categories": [
        "Uncategorized",
        "grubhub",
        "UberEATS",
        "Xfinity Rewards"
      ],
      "ts": "2026-04-23T16:36:37.000Z",
      "title_en": "Xfinity Rewards: Free $10 GrubHub Giftcard",
      "summary_en": "",
      "title_zh": "Xfinity Rewards: Free $10 GrubHub Giftcard",
      "summary_zh": "",
      "title_es": "Recompensas Xfinity: Tarjeta de regalo GrubHub de $10 gratis.",
      "summary_es": "Xfinity está regalando una tarjeta de regalo de GrubHub de $10 a sus clientes."
    },
    {
      "title": "Chase Offers: The Parking Spot, Spend $50+ & Get $10 Back",
      "url": "https://www.doctorofcredit.com/chase-offers-the-parking-spot-spend-50-get-10-back/",
      "source": "Doctor of Credit",
      "categories": [
        "Travel",
        "chase offers",
        "the parking spot"
      ],
      "ts": "2026-04-23T15:00:49.000Z",
      "title_en": "Chase Offers: The Parking Spot, Spend $50+ & Get $10 Back",
      "summary_en": "",
      "title_zh": "Chase Offers: The Parking Spot, Spend $50+ & Get $10 Back",
      "summary_zh": "",
      "title_es": "Ofertas de Chase: The Parking Spot, gasta $50+ y obtén $10 de vuelta.",
      "summary_es": "Chase ofrece un reembolso de $10 al gastar $50 o más en The Parking Spot."
    },
    {
      "title": "Recap: United Lounge Restriction, Points Events Tool & More",
      "url": "https://www.doctorofcredit.com/recap-united-lounge-restriction-points-events-tool-more/",
      "source": "Doctor of Credit",
      "categories": [
        "Recaps"
      ],
      "ts": "2026-04-23T13:00:34.000Z",
      "title_en": "Recap: United Lounge Restriction, Points Events Tool & More",
      "summary_en": "",
      "title_zh": "Recap: United Lounge Restriction, Points Events Tool & More",
      "summary_zh": "",
      "title_es": "Resumen: Restricciones en la sala VIP de United, herramienta de eventos de puntos y más.",
      "summary_es": "Se repasan las nuevas restricciones en los salones de United, junto con herramientas de eventos de puntos."
    },
    {
      "title": "Southwest Lounge Updates – Up To 5 Currently Being Planned",
      "url": "https://www.doctorofcredit.com/southwest-lounge-updates-up-to-5-currently-being-planned/",
      "source": "Doctor of Credit",
      "categories": [
        "Travel",
        "southwest"
      ],
      "ts": "2026-04-23T13:00:33.000Z",
      "title_en": "Southwest Lounge Updates – Up To 5 Currently Being Planned",
      "summary_en": "",
      "title_zh": "Southwest Lounge Updates – Up To 5 Currently Being Planned",
      "summary_zh": "",
      "title_es": "Actualizaciones de la sala VIP de Southwest – Hasta 5 están siendo planificadas actualmente.",
      "summary_es": "Southwest está planeando hasta cinco nuevas salas VIP para sus clientes."
    },
    {
      "title": "Meijer Mperks: 7,500 Points On $100 Visa Giftcard (Valid Until 4/28)",
      "url": "https://www.doctorofcredit.com/meijer-mperks-10-off-150-visa-giftcards-7/",
      "source": "Doctor of Credit",
      "categories": [
        "Deals",
        "meijer",
        "visa gift cards"
      ],
      "ts": "2026-04-23T00:45:00.000Z",
      "title_en": "Meijer Mperks: 7,500 Points On $100 Visa Giftcard (Valid Until 4/28)",
      "summary_en": "",
      "title_zh": "Meijer Mperks: 7,500 Points On $100 Visa Giftcard (Valid Until 4/28)",
      "summary_zh": "",
      "title_es": "Meijer Mperks: 7,500 puntos al comprar una tarjeta de regalo Visa de $100 (válido hasta el 28/4).",
      "summary_es": "Meijer ofrece 7,500 puntos de Mperks al comprar una tarjeta de regalo Visa de $100 antes del 28 de abril."
    },
    {
      "title": "[YMMV] Chase Business Checking: $50 Bonus For Making 15 Zelle Transactions Of $5+ Each",
      "url": "https://www.doctorofcredit.com/targeted-chase-business-checking-50-bonus-for-making-15-zelle-transactions-of-5-each/",
      "source": "Doctor of Credit",
      "categories": [
        "Credit Cards",
        "chase",
        "chase business",
        "chase business checking",
        "checking"
      ],
      "ts": "2026-04-22T23:30:56.000Z",
      "title_en": "[YMMV] Chase Business Checking: $50 Bonus For Making 15 Zelle Transactions Of $5+ Each",
      "summary_en": "",
      "title_zh": "[YMMV] Chase Business Checking: $50 Bonus For Making 15 Zelle Transactions Of $5+ Each",
      "summary_zh": "",
      "title_es": "[YMMV] Chase Business Checking: Bono de $50 al realizar 15 transacciones Zelle de $5 o más cada una.",
      "summary_es": "Chase Business Checking otorga un bono de $50 si realizas al menos 15 transferencias Zelle de $5 o más."
    },
    {
      "title": "UberEats: $25 Off $26+ (HEINZ Verified Spots), During NFL Draft (Pick 57)",
      "url": "https://www.doctorofcredit.com/ubereats-25-off-26-heinz-verified-spots-during-nfl-draft-pick-57/",
      "source": "Doctor of Credit",
      "categories": [
        "Deals",
        "Food Delivery",
        "UberEATS"
      ],
      "ts": "2026-04-22T23:21:05.000Z",
      "title_en": "UberEats: $25 Off $26+ (HEINZ Verified Spots), During NFL Draft (Pick 57)",
      "summary_en": "",
      "title_zh": "UberEats: $25 Off $26+ (HEINZ Verified Spots), During NFL Draft (Pick 57)",
      "summary_zh": "",
      "title_es": "UberEats: $25 de descuento en pedidos de $26+ (establecimientos verificados por HEINZ), durante el NFL Draft (selección 57).",
      "summary_es": "UberEats ofrece un descuento de $25 en pedidos a partir de $26 en lugares verificados por HEINZ durante el NFL Draft."
    },
    {
      "title": "[$500 Million ‘Rescue Package’] Spirit Airlines To Liquidate As Early As This Week According To Sources",
      "url": "https://www.doctorofcredit.com/spirit-airlines-to-liquidate-as-early-as-this-week/",
      "source": "Doctor of Credit",
      "categories": [
        "Travel",
        "spirit airlines"
      ],
      "ts": "2026-04-22T21:07:59.000Z",
      "title_en": "[$500 Million ‘Rescue Package’] Spirit Airlines To Liquidate As Early As This Week According To Sources",
      "summary_en": "",
      "title_zh": "[$500 Million ‘Rescue Package’] Spirit Airlines To Liquidate As Early As This Week According To Sources",
      "summary_zh": "",
      "title_es": "[‘Paquete de rescate’ de $500 millones] Spirit Airlines podría liquidarse tan pronto como esta semana, según fuentes.",
      "summary_es": "Spirit Airlines enfrenta una posible liquidación esta semana tras un rescate de $500 millones."
    },
    {
      "title": "[Targeted] Barclays Spend Bonuses – Get 5x Everywhere & Other Offers",
      "url": "https://www.doctorofcredit.com/targeted-barclays-spend-bonuses-get-5x-everywhere-other-offers/",
      "source": "Doctor of Credit",
      "categories": [
        "Credit Cards",
        "barclays",
        "spend offers"
      ],
      "ts": "2026-04-22T18:30:37.000Z",
      "title_en": "[Targeted] Barclays Spend Bonuses – Get 5x Everywhere & Other Offers",
      "summary_en": "",
      "title_zh": "[Targeted] Barclays Spend Bonuses – Get 5x Everywhere & Other Offers",
      "summary_zh": "",
      "title_es": "[Dirigido] Bonificaciones de gasto de Barclays – Obtén 5x en todas partes y otras ofertas.",
      "summary_es": "Barclays ofrece bonificaciones de gasto que incluyen 5x en todas las categorías y otras promociones."
    },
    {
      "title": "[YMMV] Safeway/Albertson’s Just4u: $40 Off $75 Online Order",
      "url": "https://www.doctorofcredit.com/ymmv-safeway-albertsons-just4u-40-off-75-online-order/",
      "source": "Doctor of Credit",
      "categories": [
        "Deals",
        "albertsons",
        "Safeway"
      ],
      "ts": "2026-04-22T18:15:09.000Z",
      "title_en": "[YMMV] Safeway/Albertson’s Just4u: $40 Off $75 Online Order",
      "summary_en": "",
      "title_zh": "[YMMV] Safeway/Albertson’s Just4u: $40 Off $75 Online Order",
      "summary_zh": "",
      "title_es": "[YMMV] Safeway/Albertson’s Just4u: $40 de descuento en pedidos en línea de $75.",
      "summary_es": "Safeway y Albertson’s ofrecen un descuento de $40 en compras en línea de al menos $75 a través de Just4u."
    },
    {
      "title": "Target: Trade In A Car Seat & Get 20% Off A New Car Seat, Stroller Or Select Baby Gear (4/19-5/2)",
      "url": "https://www.doctorofcredit.com/target-trade-in-a-car-seat-get-20-off-a-new-car-seat-stroller-or-select-baby-gear-9-21-10-4/",
      "source": "Doctor of Credit",
      "categories": [
        "Deals",
        "target"
      ],
      "ts": "2026-04-22T18:00:41.000Z",
      "title_en": "Target: Trade In A Car Seat & Get 20% Off A New Car Seat, Stroller Or Select Baby Gear (4/19-5/2)",
      "summary_en": "",
      "title_zh": "Target: Trade In A Car Seat & Get 20% Off A New Car Seat, Stroller Or Select Baby Gear (4/19-5/2)",
      "summary_zh": "",
      "title_es": "Target: Intercambia un asiento de auto para bebé y obtén 20% de descuento en un nuevo asiento, cochecito o productos seleccionados para bebé (19/4-2/5).",
      "summary_es": "Target concede un 20% de descuento en asientos de auto, cochecitos o accesorios para bebé al entregar uno usado."
    },
    {
      "title": "Chase Secure Banking $125 Checking Bonus",
      "url": "https://www.doctorofcredit.com/chase-secure-banking-100-checking-bonus/",
      "source": "Doctor of Credit",
      "categories": [
        "Bank Accounts",
        "direct deposit not required",
        "soft pull"
      ],
      "ts": "2026-04-22T18:00:27.000Z",
      "title_en": "Chase Secure Banking $125 Checking Bonus",
      "summary_en": "",
      "title_zh": "Chase Secure Banking $125 Checking Bonus",
      "summary_zh": "",
      "title_es": "Chase Secure Banking: Bono de $125 por cuenta corriente.",
      "summary_es": "Chase Secure Banking ofrece un bono de $125 al abrir una cuenta corriente."
    }
  ],
  "fetched": "2026-04-24T14:01:48.247Z"
}