{
  "items": [
    {
      "title": "Bank of America Air France/KLM FlyingBlue Card 100,000 Signup Bonus + 100 XP",
      "url": "https://www.doctorofcredit.com/bank-of-america-air-france-klm-flyingblue-card-100000-signup-bonus-100-xp/",
      "source": "Doctor of Credit",
      "categories": [
        "Credit Cards",
        "AirFrance/KLM",
        "bank of america",
        "bank of america airfrance/klm",
        "big",
        "credit card bonuses"
      ],
      "ts": "2026-07-23T01:13:15.000Z",
      "title_en": "Bank of America Air France/KLM FlyingBlue Card 100,000 Signup Bonus + 100 XP",
      "summary_en": "",
      "title_zh": "美國銀行 Air France/KLM FlyingBlue 卡 100,000 飛行里數註冊獎勵 + 100 XP",
      "summary_zh": "新戶持卡可獲得 100,000 飛行里數與 100 XP 的註冊獎勵。",
      "title_es": "Tarjeta FlyingBlue de Air France/KLM de Bank of America: Bono de bienvenida de 100,000 + 100 XP",
      "summary_es": "La tarjeta FlyingBlue de Bank of America ofrece un bono de inscripción de 100,000 puntos más 100 XP para nuevos usuarios."
    },
    {
      "title": "[New Customers] Mint Mobile: 128GB Google Pixel 10 (Locked) + 12-Mo Unlimited Plan For $328 [Stack With CO Offers For $45 Off)",
      "url": "https://www.doctorofcredit.com/new-customers-mint-mobile-128gb-google-pixel-10-locked-12-mo-unlimited-plan-for-328/",
      "source": "Doctor of Credit",
      "categories": [
        "Deals",
        "google pixel",
        "mint",
        "mint mobile",
        "pixel",
        "pixel 10"
      ],
      "ts": "2026-07-23T00:38:26.000Z",
      "title_en": "[New Customers] Mint Mobile: 128GB Google Pixel 10 (Locked) + 12-Mo Unlimited Plan For $328 [Stack With CO Offers For $45 Off)",
      "summary_en": "",
      "title_zh": "[新客戶] Mint Mobile：128GB Google Pixel 10（鎖定版）+ 12 個月無限方案，售價 $328 [配合優惠最高可減 $45]",
      "summary_zh": "新客戶購買 Mint Mobile 的 Pixel 10 手機與 12 個月無限方案，原價 $328，若結合優惠最高可減 $45。",
      "title_es": "Mint Mobile: Google Pixel 10 de 128GB (Bloqueado) + Plan Ilimitado de 12 meses por $328 [Combina con ofertas CO para $45 de descuento]",
      "summary_es": "Mint Mobile incluye un Google Pixel 10 bloqueado con 128GB y un plan ilimitado de 12 meses por $328, con posibilidad de ahorrar $45 al combinar otras ofertas."
    },
    {
      "title": "TastyTrade 3% Transfer Bonus – Up To $3,000 Bonus (36 Month Hold)",
      "url": "https://www.doctorofcredit.com/tastytrade-3-transfer-bonus-up-to-3000-bonus-36-month-hold/",
      "source": "Doctor of Credit",
      "categories": [
        "Bank Accounts",
        "brokerage bonuses",
        "tastyworks"
      ],
      "ts": "2026-07-22T23:54:10.000Z",
      "title_en": "TastyTrade 3% Transfer Bonus – Up To $3,000 Bonus (36 Month Hold)",
      "summary_en": "",
      "title_zh": "TastyTrade 3% 轉帳獎金 – 最高 $3,000 獎金（36 個月持有）",
      "summary_zh": "在 TastyTrade 進行轉帳可獲 3% 獎金，最高可達 $3,000，且需持有 36 個月。",
      "title_es": "TastyTrade: Bono de transferencia del 3% – Hasta $3,000 de bono (retención de 36 meses)",
      "summary_es": "TastyTrade devuelve un 3% sobre las transferencias hasta $3,000, con la condición de mantener el dinero invertido durante 36 meses."
    },
    {
      "title": "Alaska, Delta, American, Southwest, United Shopping Portals: Earn Up To 11,500 Bonus Miles",
      "url": "https://www.doctorofcredit.com/united-shopping-portal-earn-up-to-2500-bonus-miles/",
      "source": "Doctor of Credit",
      "categories": [
        "Deals",
        "shopping portals",
        "united"
      ],
      "ts": "2026-07-22T21:45:14.000Z",
      "title_en": "Alaska, Delta, American, Southwest, United Shopping Portals: Earn Up To 11,500 Bonus Miles",
      "summary_en": "",
      "title_zh": "Alaska、Delta、American、Southwest、United 購物門戶：可獲得最高 11,500 飛行里數獎勵",
      "summary_zh": "透過這些航空公司的購物門戶消費，最多可賺取 11,500 免費里數。",
      "title_es": "Alaska, Delta, American, Southwest, United Portales de compras: Gana hasta 11,500 millas bonus",
      "summary_es": "Los portales de compras de Alaska, Delta, American, Southwest y United permiten acumular hasta 11,500 millas bonus en cada compra."
    },
    {
      "title": "T-Mobile $250 Referral Bonus For Each Party",
      "url": "https://www.doctorofcredit.com/t-mobile-250-referral-bonus-for-each-party/",
      "source": "Doctor of Credit",
      "categories": [
        "Deals",
        "t-mobile"
      ],
      "ts": "2026-07-22T21:05:44.000Z",
      "title_en": "T-Mobile $250 Referral Bonus For Each Party",
      "summary_en": "",
      "title_zh": "T-Mobile 每位推薦人可獲 $250 獎金",
      "summary_zh": "每成功推薦一位新用戶，T-Mobile 將給予 $250 的推薦獎金。",
      "title_es": "T-Mobile: Bono de referido de $250 por cada parte",
      "summary_es": "T-Mobile paga $250 por cada referido que se registre exitosamente en su servicio."
    },
    {
      "title": "Kroger / Harris Teeter: 4x Fuel Points On Select Third Party Gift Cards (7/24 – 7/25)",
      "url": "https://www.doctorofcredit.com/kroger-harris-teeter-stores-4x-fuel-points-on-select-gift-cards-includes-fixed-visa-mc-10-7-10-20/",
      "source": "Doctor of Credit",
      "categories": [
        "Deals",
        "fuel points",
        "gift card deals",
        "kroger",
        "mastercard gift cards",
        "visa gift cards"
      ],
      "ts": "2026-07-22T21:00:50.000Z",
      "title_en": "Kroger / Harris Teeter: 4x Fuel Points On Select Third Party Gift Cards (7/24 – 7/25)",
      "summary_en": "",
      "title_zh": "Kroger / Harris Teeter：精選第三方禮品卡 4 倍燃油點數（7/24 – 7/25）",
      "summary_zh": "在 Kroger 或 Harris Teeter 購買特定第三方禮品卡，可獲得 4 倍燃油點數，優惠期限至 7 月 25 日。",
      "title_es": "Kroger / Harris Teeter: 4x Puntos de combustible en tarjetas de regalo de terceros seleccionadas (24/7 – 25/7)",
      "summary_es": "Kroger y Harris Teeter ofrecen quadruplicar los puntos de combustible en tarjetas de regalo de terceros durante el fin de semana del 24 al 25 de julio."
    },
    {
      "title": "Target.com: Buy $100 DoorDash eGiftcard & Get $20 Target eGiftcard",
      "url": "https://www.doctorofcredit.com/target-com-buy-100-doordash-egiftcard-get-20-target-egiftcard/",
      "source": "Doctor of Credit",
      "categories": [
        "Gift Card Deals",
        "doordash",
        "target"
      ],
      "ts": "2026-07-22T17:10:16.000Z",
      "title_en": "Target.com: Buy $100 DoorDash eGiftcard & Get $20 Target eGiftcard",
      "summary_en": "",
      "title_zh": "Target.com：購買 $100 DoorDash 電子禮品卡即送 $20 Target 電子禮品卡",
      "summary_zh": "在 Target.com 購買價值 $100 的 DoorDash 電子禮品卡，即可獲得 $20 的 Target 電子禮品卡。",
      "title_es": "Target.com: Compra una eGiftcard de DoorDash de $100 y obtén una eGiftcard de Target de $20",
      "summary_es": "Al comprar una tarjeta de regalo digital de DoorDash por $100 en Target.com, se recibe una tarjeta de regalo de Target por $20."
    },
    {
      "title": "(Live) Robinhood Platinum Card – Full Review: $695 Annual Fee, No Signup Bonus, 5% on Dining, $1,000 Travel Credits & More",
      "url": "https://www.doctorofcredit.com/live-robinhood-platinum-card-full-review-695-fee-no-bonus-5-dining-1000-travel-credits-more/",
      "source": "Doctor of Credit",
      "categories": [
        "Credit Cards",
        "big",
        "new credit cards",
        "robinhood",
        "robinhood platinum"
      ],
      "ts": "2026-07-22T17:03:19.000Z",
      "title_en": "(Live) Robinhood Platinum Card – Full Review: $695 Annual Fee, No Signup Bonus, 5% on Dining, $1,000 Travel Credits & More",
      "summary_en": "",
      "title_zh": "美國銀行 Air France/KLM FlyingBlue 卡 70,000 飛行里數註冊獎勵 + 100 XP（另有升級福利）",
      "summary_zh": "此卡新戶可獲得 70,000 飛行里數與 100 XP，並享有增強福利。",
      "title_es": "Robinhood Platinum Card – Revisión completa: Tarifa anual de $695, sin bono de bienvenida, 5% en restaurantes, $1,000 en créditos de viaje y más",
      "summary_es": "La Robinhood Platinum Card tiene una tarifa anual de $695, no ofrece bono de bienvenida, pero proporciona 5% de cashback en restaurantes y $1,000 en créditos de viaje."
    },
    {
      "title": "Bank of America Air France/KLM FlyingBlue Card 70,000 Signup Bonus + 100 XP (Plus, Enhanced Benefits)",
      "url": "https://www.doctorofcredit.com/bank-of-america-air-france-klm-flyingblue-card-70000-signup-bonus-100-xp-plus-enhanced-benefits/",
      "source": "Doctor of Credit",
      "categories": [
        "Bank Accounts",
        "AirFrance/KLM",
        "big",
        "credit card bonuses"
      ],
      "ts": "2026-07-22T14:30:46.000Z",
      "title_en": "Bank of America Air France/KLM FlyingBlue Card 70,000 Signup Bonus + 100 XP (Plus, Enhanced Benefits)",
      "summary_en": "",
      "title_zh": "Amazon P&G 產品滿 $80 可減 $20，並可與 $25 P&G 回扣及 $3 優惠券疊加（包含 Bounty、Tide、Pampers、Cascade 等）",
      "summary_zh": "在 Amazon 購買 P&G 品牌商品滿 $80 可減 $20，若結合 $25 回扣與 $3 優惠券，最高可省更多。",
      "title_es": "Tarjeta FlyingBlue de Bank of America – Air France/KLM: Bono de bienvenida de 70,000 + 100 XP (además, beneficios mejorados)",
      "summary_es": "Esta versión de la tarjeta FlyingBlue otorga 70,000 puntos de bienvenida más 100 XP e incluye beneficios mejorados."
    },
    {
      "title": "Amazon $20 Off $80 P&G Products, Stack With $25 P&G Rebate & $3 Coupon (Bounty, Tide, Pampers, Cascade & More)",
      "url": "https://www.doctorofcredit.com/amazon-20-off-80-pg-products-stack-with-15-pg-rebate-bounty-tide-pampers-cascade-more/",
      "source": "Doctor of Credit",
      "categories": [
        "Deals",
        "amazon"
      ],
      "ts": "2026-07-22T13:45:14.000Z",
      "title_en": "Amazon $20 Off $80 P&G Products, Stack With $25 P&G Rebate & $3 Coupon (Bounty, Tide, Pampers, Cascade & More)",
      "summary_en": "",
      "title_zh": "Rakuten 星期三特惠：7 月 22 日 Viator 20% 折扣",
      "summary_zh": "Rakuten 會員在本週三（7 月 22 日）於 Viator 預訂行程可享 20% 折扣。",
      "title_es": "Amazon: $20 de descuento en $80 de productos P&G, combínalo con reembolso de $25 y cupón de $3 (Bounty, Tide, Pampers, Cascade y más)",
      "summary_es": "Amazon aplica un descuento de $20 en compras de productos P&G de al menos $80, que se puede acumular con un reembolso de $25 y un cupón de $3."
    },
    {
      "title": "Rakuten Wednesday’s: 20% At Viator On July 22nd",
      "url": "https://www.doctorofcredit.com/rakuten-wednesdays-7-at-lowes-on-july-1st/",
      "source": "Doctor of Credit",
      "categories": [
        "Deals",
        "lowes",
        "rakuten"
      ],
      "ts": "2026-07-22T13:30:18.000Z",
      "title_en": "Rakuten Wednesday’s: 20% At Viator On July 22nd",
      "summary_en": "",
      "title_zh": "DoorDash DashPass 會員：在 Starbucks、Chipotle、Safeway、Airbnb、Lowe’s 等消費可享 10% 回饋",
      "summary_zh": "DashPass 會員在指定商家消費可獲得 10% 的現金回饋。",
      "title_es": "Rakuten Miércoles: 20% de descuento en Viator el 22 de julio",
      "summary_es": "Rakuten ofrece un 20% de descuento en actividades de Viator durante el miércoles 22 de julio."
    },
    {
      "title": "DoorDash DashPass Members: 10% Back on Starbucks, Chipotle, Safeway, Airbnb, Lowe’s & More",
      "url": "https://www.doctorofcredit.com/doordash-save-15-off-many-egiftcard-brands-starbucks-zift-amazon-lowes-doordash-walgreens-outback-and-many-more/",
      "source": "Doctor of Credit",
      "categories": [
        "Gift Card Deals",
        "doordash"
      ],
      "ts": "2026-07-22T13:20:54.000Z",
      "title_en": "DoorDash DashPass Members: 10% Back on Starbucks, Chipotle, Safeway, Airbnb, Lowe’s & More",
      "summary_en": "",
      "title_zh": "OnePay：每週三每加侖汽油回饋 $1（上限 50 加侖，每日可兌換 2 次）",
      "summary_zh": "OnePay 用戶每週三加油可享每加侖 $1 的現金回饋，最高 50 加侖，每日可兌換兩次。",
      "title_es": "Miembros de DashPass en DoorDash: 10% de devolución en Starbucks, Chipotle, Safeway, Airbnb, Lowe’s y más",
      "summary_es": "Los suscriptores de DashPass reciben un 10% de devolución en compras en Starbucks, Chipotle, Safeway, Airbnb, Lowe’s y otras marcas."
    },
    {
      "title": "OnePay: $1 Cashback Per Gallon Of Gas Every Wednesday (50 Gallons, Two Redemptions Per Day)",
      "url": "https://www.doctorofcredit.com/onepay-1-cashback-per-gallon-of-gas-every-wednesday-50-gallons-two-redemptions-per-day/",
      "source": "Doctor of Credit",
      "categories": [
        "Deals",
        "fuel",
        "gas",
        "gas stations",
        "onepay"
      ],
      "ts": "2026-07-22T04:01:18.000Z",
      "title_en": "OnePay: $1 Cashback Per Gallon Of Gas Every Wednesday (50 Gallons, Two Redemptions Per Day)",
      "summary_en": "",
      "title_zh": "Befrugal：透過瀏覽器插件消費 $10 即得 $3 獎金",
      "summary_zh": "使用 Befrugal 瀏覽器插件購物滿 $10，可獲得 $3 的獎勵。",
      "title_es": "OnePay: $1 de cashback por galón de gasolina cada miércoles (50 galones, dos canjes por día)",
      "summary_es": "OnePay devuelve $1 por cada galón de gasolina hasta 50 galones los miércoles, permitiendo dos canjes diarios."
    },
    {
      "title": "Befrugal: Shop $10 Via Browser Extension & Get $3 Bonus",
      "url": "https://www.doctorofcredit.com/befrugal-shop-25-get-5-bonus/",
      "source": "Doctor of Credit",
      "categories": [
        "Deals",
        "befrugal"
      ],
      "ts": "2026-07-22T00:10:02.000Z",
      "title_en": "Befrugal: Shop $10 Via Browser Extension & Get $3 Bonus",
      "summary_en": "",
      "title_zh": "新聞信選項 – 即時、每日與每週",
      "summary_zh": "提供即時、每日與每週三種新聞信訂閱方式，方便依需求獲取最新資訊。",
      "title_es": "Befrugal: Compra $10 mediante extensión del navegador y obtén $3 de bonificación",
      "summary_es": "Befrugal bonifica con $3 cada vez que se realice una compra de $10 a través de su extensión de navegador."
    },
    {
      "title": "Newsletter Options – Instant, Daily & Weekly",
      "url": "https://www.doctorofcredit.com/newsletter-options-instant-daily-weekly/",
      "source": "Doctor of Credit",
      "categories": [
        "Site News",
        "Site news"
      ],
      "ts": "2026-07-21T22:06:14.000Z",
      "title_en": "Newsletter Options – Instant, Daily & Weekly",
      "summary_en": "",
      "title_zh": "Newsletter Options – Instant, Daily & Weekly",
      "summary_zh": "",
      "title_es": "Opciones del boletín – Instantáneo, Diario y Semanal",
      "summary_es": "Los lectores pueden elegir recibir el boletín de noticias de forma instantánea, diaria o semanal."
    }
  ],
  "fetched": "2026-07-23T02:09:47.247Z"
}