{
  "items": [
    {
      "title": "[NY] Suffolk Federal Credit Union $500 Checking Bonus",
      "url": "https://www.doctorofcredit.com/ny-suffolk-federal-credit-union-100-checking-bonus-direct-deposit-not-required/",
      "source": "Doctor of Credit",
      "categories": [
        "Bank Accounts",
        "credit card funding",
        "direct deposit not required",
        "ny bank bonuses"
      ],
      "ts": "2026-05-31T14:00:41.000Z",
      "title_en": "[NY] Suffolk Federal Credit Union $500 Checking Bonus",
      "summary_en": "",
      "title_zh": "[NY] Suffolk Federal Credit Union $500 Checking Bonus",
      "summary_zh": "",
      "title_es": "[NY] Suffolk Federal Credit Union Bono de $500 por Cuenta Corriente",
      "summary_es": "Suffolk Federal Credit Union ofrece un bono de $500 por abrir una cuenta corriente en Nueva York."
    },
    {
      "title": "[AL Only] Alabama Central Credit Union $100 Referral Bonus, Direct Deposit Not Required",
      "url": "https://www.doctorofcredit.com/al-only-alabama-central-credit-union-100-referral-bonus-direct-deposit-not-required/",
      "source": "Doctor of Credit",
      "categories": [
        "Bank Accounts",
        "al bank bonuses",
        "direct deposit required"
      ],
      "ts": "2026-05-31T13:30:54.000Z",
      "title_en": "[AL Only] Alabama Central Credit Union $100 Referral Bonus, Direct Deposit Not Required",
      "summary_en": "",
      "title_zh": "[AL Only] Alabama Central Credit Union $100 Referral Bonus, Direct Deposit Not Required",
      "summary_zh": "",
      "title_es": "[AL] Alabama Central Credit Union Bono de $100 por Referencia, No Requiere Depósito Directo",
      "summary_es": "Alabama Central Credit Union ofrece un bono de $100 por cada referido sin necesidad de hacer un depósito directo en Alabama."
    },
    {
      "title": "Staples: No Purchase Fee On $200 Visa Gift Cards (5/31-6/5)",
      "url": "https://www.doctorofcredit.com/staples-no-purchase-fee-on-200-visa-gift-cards-10-31-11-6-limit-5/",
      "source": "Doctor of Credit",
      "categories": [
        "Manufactured Spending",
        "staples",
        "visa gift cards"
      ],
      "ts": "2026-05-31T13:00:28.000Z",
      "title_en": "Staples: No Purchase Fee On $200 Visa Gift Cards (5/31-6/5)",
      "summary_en": "",
      "title_zh": "Staples: No Purchase Fee On $200 Visa Gift Cards (5/31-6/5)",
      "summary_zh": "",
      "title_es": "Staples: Sin Cargo de Compra en Tarjetas de Regalo Visa de $200 (5/31-6/5)",
      "summary_es": "Staples permite obtener tarjetas de regalo Visa de $200 sin cargo adicional durante el período del 31 de mayo al 5 de junio."
    },
    {
      "title": "[IA Only] FSB Bank $300-$1,000 Business Checking Bonus (Requires Payroll Processing)",
      "url": "https://www.doctorofcredit.com/ia-only-fsb-bank-500-business-checking-bonus-requires-payroll-processing/",
      "source": "Doctor of Credit",
      "categories": [
        "Bank Accounts",
        "direct deposit not required",
        "ia bank bonuses"
      ],
      "ts": "2026-05-31T12:00:30.000Z",
      "title_en": "[IA Only] FSB Bank $300-$1,000 Business Checking Bonus (Requires Payroll Processing)",
      "summary_en": "",
      "title_zh": "[IA Only] FSB Bank $300-$1,000 Business Checking Bonus (Requires Payroll Processing)",
      "summary_zh": "",
      "title_es": "[IA] FSB Bank Bono de $300‑$1,000 por Cuenta Corriente Empresarial (Requiere Procesamiento de Nómina)",
      "summary_es": "FSB Bank ofrece un bono entre $300 y $1,000 para cuentas corrientes empresariales en Iowa, siempre que se procese la nómina a través del banco."
    },
    {
      "title": "[MS Only] Grand Bank $200 Checking Bonus",
      "url": "https://www.doctorofcredit.com/ms-only-grand-bank-200-checking-bonus/",
      "source": "Doctor of Credit",
      "categories": [
        "Bank Accounts",
        "direct deposit required",
        "ms bank bonuses"
      ],
      "ts": "2026-05-30T23:13:45.000Z",
      "title_en": "[MS Only] Grand Bank $200 Checking Bonus",
      "summary_en": "",
      "title_zh": "[MS Only] Grand Bank $200 Checking Bonus",
      "summary_zh": "",
      "title_es": "[MS] Grand Bank Bono de $200 por Cuenta Corriente",
      "summary_es": "Grand Bank en Mississippi ofrece un bono de $200 por abrir una cuenta corriente."
    },
    {
      "title": "[MN, WI, MI, WI, FL, GA] Wings Credit Union $500 Checking Bonus + $100 Referral",
      "url": "https://www.doctorofcredit.com/mn-wi-mi-fl-ga-wings-credit-union-300-checking-bonus/",
      "source": "Doctor of Credit",
      "categories": [
        "Bank Accounts",
        "credit card funding",
        "direct deposit required",
        "fl bank bonuses",
        "ga bank bonuses",
        "mi bank bonuses",
        "mn bank bonuses",
        "soft pull",
        "wi bank bonuses"
      ],
      "ts": "2026-05-30T23:05:50.000Z",
      "title_en": "[MN, WI, MI, WI, FL, GA] Wings Credit Union $500 Checking Bonus + $100 Referral",
      "summary_en": "",
      "title_zh": "[MN, WI, MI, WI, FL, GA] Wings Credit Union $500 Checking Bonus + $100 Referral",
      "summary_zh": "",
      "title_es": "[MN, WI, MI, FL, GA] Wings Credit Union Bono de $500 por Cuenta Corriente + $100 por Referencia",
      "summary_es": "Wings Credit Union ofrece un bono de $500 por cuenta corriente más $100 por cada referido en varios estados."
    },
    {
      "title": "[MA & CT only] PeoplesBank (Bankatpeoples) $350 Checking Bonus",
      "url": "https://www.doctorofcredit.com/ma-ct-only-peoplesbank-bankatpeoples-250-checking-bonus-direct-deposit-not-required/",
      "source": "Doctor of Credit",
      "categories": [
        "Bank Accounts",
        "credit card funding",
        "ct bank bonuses",
        "direct deposit not required",
        "ma bank bonuses",
        "soft pull"
      ],
      "ts": "2026-05-30T23:00:09.000Z",
      "title_en": "[MA & CT only] PeoplesBank (Bankatpeoples) $350 Checking Bonus",
      "summary_en": "",
      "title_zh": "[MA & CT only] PeoplesBank (Bankatpeoples) $350 Checking Bonus",
      "summary_zh": "",
      "title_es": "[MA y CT] PeoplesBank (Bankatpeoples) Bono de $350 por Cuenta Corriente",
      "summary_es": "PeoplesBank ofrece un bono de $350 por abrir una cuenta corriente para clientes en Massachusetts y Connecticut."
    },
    {
      "title": "[CO & ID, In Branch Only] First Interstate Bank $400 Business Checking",
      "url": "https://www.doctorofcredit.com/co-id-in-branch-only-first-interstate-bank-400-business-checking/",
      "source": "Doctor of Credit",
      "categories": [
        "Bank Accounts",
        "co bank bonuses",
        "credit card funding",
        "id bank bonuses"
      ],
      "ts": "2026-05-30T22:46:33.000Z",
      "title_en": "[CO & ID, In Branch Only] First Interstate Bank $400 Business Checking",
      "summary_en": "",
      "title_zh": "[CO & ID, In Branch Only] First Interstate Bank $400 Business Checking",
      "summary_zh": "",
      "title_es": "[CO e ID, Solo en Sucursal] First Interstate Bank Bono de $400 por Cuenta Corriente Empresarial",
      "summary_es": "First Interstate Bank ofrece un bono de $400 por una cuenta corriente empresarial solo en sus sucursales de Colorado e Idaho."
    },
    {
      "title": "[PA & OH, In Branch] S&T Bank $400-$600 Business Checking Bonus",
      "url": "https://www.doctorofcredit.com/pa-oh-st-bank-600-business-checking-bonus-requires-payment-processing/",
      "source": "Doctor of Credit",
      "categories": [
        "Bank Accounts",
        "credit card funding",
        "direct deposit not required",
        "oh bank bonuses",
        "pa bank bonuses",
        "soft pull"
      ],
      "ts": "2026-05-30T22:31:11.000Z",
      "title_en": "[PA & OH, In Branch] S&T Bank $400-$600 Business Checking Bonus",
      "summary_en": "",
      "title_zh": "[PA & OH, In Branch] S&T Bank $400-$600 Business Checking Bonus",
      "summary_zh": "",
      "title_es": "[PA y OH, Solo en Sucursal] S&T Bank Bono de $400‑$600 por Cuenta Corriente Empresarial",
      "summary_es": "S&T Bank ofrece un bono entre $400 y $600 por abrir una cuenta corriente empresarial en Pensilvania y Ohio, disponible solo en sucursal."
    },
    {
      "title": "[6/5] Tropical Smoothie Cafe: Free 12oz Mango Monsoon Smoothie When You Wear Flip Flops",
      "url": "https://www.doctorofcredit.com/6-5-tropical-smoothie-cafe-free-12oz-mango-monsoon-smoothie-when-you-wear-flip-flops/",
      "source": "Doctor of Credit",
      "categories": [
        "Deals",
        "free drinks",
        "freebies",
        "tropical smoothie cafe"
      ],
      "ts": "2026-05-30T20:56:14.000Z",
      "title_en": "[6/5] Tropical Smoothie Cafe: Free 12oz Mango Monsoon Smoothie When You Wear Flip Flops",
      "summary_en": "",
      "title_zh": "[6/5] Tropical Smoothie Cafe: Free 12oz Mango Monsoon Smoothie When You Wear Flip Flops",
      "summary_zh": "",
      "title_es": "[6/5] Tropical Smoothie Cafe: Smoothie Mango Monsoon de 12oz Gratis al Llevar Sandalias",
      "summary_es": "Tropical Smoothie Cafe regalará un smoothie de mango de 12 onzas a quienes lleven sandalias el 5 de junio."
    },
    {
      "title": "[OH] OUCU Financial $100 Referral Bonus",
      "url": "https://www.doctorofcredit.com/oh-oucu-financial-100-referral-bonus/",
      "source": "Doctor of Credit",
      "categories": [
        "Bank Accounts",
        "direct deposit required",
        "oh bank bonuses"
      ],
      "ts": "2026-05-30T18:30:33.000Z",
      "title_en": "[OH] OUCU Financial $100 Referral Bonus",
      "summary_en": "",
      "title_zh": "[OH] OUCU Financial $100 Referral Bonus",
      "summary_zh": "",
      "title_es": "[OH] OUCU Financial Bono de $100 por Referencia",
      "summary_es": "OUCU Financial en Ohio ofrece un bono de $100 por cada cliente referido."
    },
    {
      "title": "[NJ only] Columbia Bank $300 Checking Account Bonus/$400 Savings Bonus",
      "url": "https://www.doctorofcredit.com/nj-columbia-bank-200-chehking-account-bonus/",
      "source": "Doctor of Credit",
      "categories": [
        "Bank Accounts",
        "credit card funding",
        "direct deposit required",
        "nj bank bonuses",
        "soft pull"
      ],
      "ts": "2026-05-30T17:00:05.000Z",
      "title_en": "[NJ only] Columbia Bank $300 Checking Account Bonus/$400 Savings Bonus",
      "summary_en": "",
      "title_zh": "[NJ only] Columbia Bank $300 Checking Account Bonus/$400 Savings Bonus",
      "summary_zh": "",
      "title_es": "[NJ] Columbia Bank Bono de $300 por Cuenta Corriente / $400 por Cuenta de Ahorros",
      "summary_es": "Columbia Bank ofrece un bono de $300 por abrir una cuenta corriente y $400 por una cuenta de ahorros en Nueva Jersey."
    },
    {
      "title": "[OR, WA] Red Canoe Credit Union $150 Checking Bonus, Direct Deposit Not Required",
      "url": "https://www.doctorofcredit.com/or-wa-red-canoe-credit-union-150-checking-bonus-direct-deposit-not-required/",
      "source": "Doctor of Credit",
      "categories": [
        "Bank Accounts",
        "direct deposit not required",
        "or bank bonuses",
        "wa bank bonuses"
      ],
      "ts": "2026-05-30T16:30:04.000Z",
      "title_en": "[OR, WA] Red Canoe Credit Union $150 Checking Bonus, Direct Deposit Not Required",
      "summary_en": "",
      "title_zh": "[OR, WA] Red Canoe Credit Union $150 Checking Bonus, Direct Deposit Not Required",
      "summary_zh": "",
      "title_es": "[OR, WA] Red Canoe Credit Union Bono de $150 por Cuenta Corriente, No Requiere Depósito Directo",
      "summary_es": "Red Canoe Credit Union ofrece un bono de $150 por cuenta corriente en Oregón y Washington sin necesidad de depósito directo."
    },
    {
      "title": "[IL & In Branch Only] State Bank of Bement $100 Checking Bonus",
      "url": "https://www.doctorofcredit.com/il-branch-state-bank-bement-100-checking-bonus/",
      "source": "Doctor of Credit",
      "categories": [
        "Bank Accounts",
        "direct deposit required",
        "IL bank bonuses"
      ],
      "ts": "2026-05-30T16:00:42.000Z",
      "title_en": "[IL & In Branch Only] State Bank of Bement $100 Checking Bonus",
      "summary_en": "",
      "title_zh": "[IL & In Branch Only] State Bank of Bement $100 Checking Bonus",
      "summary_zh": "",
      "title_es": "[IL, Solo en Sucursal] State Bank of Bement Bono de $100 por Cuenta Corriente",
      "summary_es": "State Bank of Bement ofrece un bono de $100 por cuenta corriente solo en sus sucursales de Illinois."
    },
    {
      "title": "[MA] Cambridge Savings Bank $800 Checking Bonus + $400 Savings",
      "url": "https://www.doctorofcredit.com/ma-ct-me-nh-ri-vt-cambridge-savings-bank-400-checking-bonus/",
      "source": "Doctor of Credit",
      "categories": [
        "Bank Accounts"
      ],
      "ts": "2026-05-30T14:45:20.000Z",
      "title_en": "[MA] Cambridge Savings Bank $800 Checking Bonus + $400 Savings",
      "summary_en": "",
      "title_zh": "[MA] Cambridge Savings Bank $800 Checking Bonus + $400 Savings",
      "summary_zh": "",
      "title_es": "[MA] Cambridge Savings Bank Bono de $800 por Cuenta Corriente + $400 por Cuenta de Ahorros",
      "summary_es": "Cambridge Savings Bank ofrece un bono de $800 por abrir una cuenta corriente y $400 por una cuenta de ahorros en Massachusetts."
    }
  ],
  "fetched": "2026-05-31T14:10:35.453Z"
}