{
  "saved": 10,
  "failed": 0,
  "report": [
    {
      "cardId": "chase-sapphire-reserve",
      "status": "ok",
      "fee": 795,
      "bonus": 125000
    },
    {
      "cardId": "chase-sapphire-preferred",
      "status": "ok",
      "fee": 95,
      "bonus": 75000
    },
    {
      "cardId": "amex-platinum-personal",
      "status": "ok",
      "fee": 695,
      "bonus": 175000
    },
    {
      "cardId": "amex-hilton-aspire",
      "status": "ok",
      "fee": 450,
      "bonus": 175000
    },
    {
      "cardId": "amex-hilton-honors",
      "status": "ok",
      "fee": 2026,
      "bonus": 70000
    },
    {
      "cardId": "amex-hilton-surpass",
      "status": "ok",
      "fee": 95,
      "bonus": 130000
    },
    {
      "cardId": "citi-strata-elite",
      "status": "ok",
      "fee": 200,
      "bonus": 100000
    },
    {
      "cardId": "discover-it",
      "status": "ok",
      "fee": 2022
    },
    {
      "cardId": "bofa-travel-rewards",
      "status": "ok",
      "fee": 2026,
      "bonus": 20000
    },
    {
      "cardId": "apple-card",
      "status": "ok",
      "fee": 2024
    }
  ],
  "updated": "2026-04-12T17:47:21.006Z"
}